huble/__init__.py
huble/automl/__init__.py
huble/automl/automl.py
huble/connector/__init__.py
huble/connector/dataset.py
huble/connector/deployment.py
huble/connector/experiment.py
huble/error/__init__.py
huble/error/decorators.py
huble/error/exceptions.py
huble/main.py
huble/sklearn/__init__.py
huble/sklearn/essentials/__init__.py
huble/sklearn/essentials/essentail_params.ts
huble/sklearn/essentials/function.py
huble/sklearn/essentials/handler.py
huble/sklearn/evaluate.py
huble/sklearn/generate.py
huble/sklearn/graph.py
huble/sklearn/metrics/__init__.py
huble/sklearn/metrics/metrics.py
huble/sklearn/process/__init__.py
huble/sklearn/process/functions.py
huble/sklearn/process/handler.py
huble/sklearn/process/preprocess_params.ts
huble/sklearn/train/__init__.py
huble/sklearn/train/functions.py
huble/sklearn/train/handler.py
huble/sklearn/train/model_params.ts
huble/util/__init__.py
huble/util/convert_to_reactflow_graph.py
huble/util/data_types.py
huble/util/feature_selection.py
huble/util/inference_pipeline.py
huble/util/recommend_model.py
huble/util/typed_params.py
huble/util/verify_builder_pipeline.py
huble/util/verify_ml.py
huble-0.2.2992.dist-info/WHEEL
huble-0.2.2992.dist-info/METADATA
huble-0.2.2992.dist-info/RECORD
