Metadata-Version: 2.1
Name: huble
Version: 0.2.2992
Summary: 
Author: Rugz007
Author-email: rugvedsomwanshi007@gmail.com
Maintainer: Arjit Agarwal
Maintainer-email: arjitagarwal123@gmail.com
Requires-Python: >=3.8.1,<3.10
Classifier: Programming Language :: Python :: 3
Classifier: Programming Language :: Python :: 3.9
Requires-Dist: black (>=22.8.0,<23.0.0)
Requires-Dist: boto3 (>=1.26.63,<2.0.0)
Requires-Dist: datacleaner (>=0.1.5,<0.2.0)
Requires-Dist: evalml (>=0.67.0,<0.68.0)
Requires-Dist: kaleido (==0.2.1)
Requires-Dist: pandas (>=1.3.5,<2.0.0)
Requires-Dist: pydantic (>=1.10.4,<2.0.0)
Requires-Dist: scikit-learn (==1.1.2)
Requires-Dist: scipy (>=1.7.0,<1.8.0)
